django_pdf_overlay/__init__.py
django_pdf_overlay/app_settings.py
django_pdf_overlay/apps.py
django_pdf_overlay/commands.py
django_pdf_overlay/forms.py
django_pdf_overlay/models.py
django_pdf_overlay/signals.py
django_pdf_overlay/urls.py
django_pdf_overlay/utils.py
django_pdf_overlay/validators.py
django_pdf_overlay/views.py
django_pdf_overlay/migrations/0001_initial.py
django_pdf_overlay/migrations/__init__.py
django_pdf_overlay/templates/django_pdf_overlay/base.html
django_pdf_overlay/templates/django_pdf_overlay/document_confirm_delete.html
django_pdf_overlay/templates/django_pdf_overlay/document_detail.html
django_pdf_overlay/templates/django_pdf_overlay/document_form.html
django_pdf_overlay/templates/django_pdf_overlay/document_list.html
django_pdf_overlay/templates/django_pdf_overlay/field_editor.html
django_pdf_overlay/templates/django_pdf_overlay/field_layout.html
django_pdf_overlay/templates/django_pdf_overlay/page_form.html
django_pdf_overlay/tests/__init__.py
django_pdf_overlay/tests/base_test_classes.py
django_pdf_overlay/tests/test_commands.py
django_pdf_overlay/tests/test_general.py
django_pdf_overlay/tests/test_models.py
django_pdf_overlay/tests/test_utils.py
django_pdf_overlay/tests/fixtures/sample.pdf
django_pdf_overlay-1.1.0.dist-info/LICENSE
django_pdf_overlay-1.1.0.dist-info/METADATA
django_pdf_overlay-1.1.0.dist-info/WHEEL
django_pdf_overlay-1.1.0.dist-info/top_level.txt
django_pdf_overlay-1.1.0.dist-info/RECORD
