Metadata-Version: 2.1
Name: django-pdf-overlay
Version: 1.1.0
Summary: Fill PDFs from model instances
Home-page: http://github.com/iarp/django-pdf-overlay
Author: IARP
Author-email: iarp.opensource@gmail.com
License: UNKNOWN
Project-URL: Documentation, https://django-pdf-overlay.readthedocs.io/en/latest/
Project-URL: Source, https://github.com/iarp/django-pdf-overlay/
Project-URL: Tracker, https://github.com/iarp/django-pdf-overlay/issues
Keywords: django pdf overlay
Platform: UNKNOWN
Classifier: Development Status :: 4 - Beta
Classifier: Intended Audience :: Developers
Classifier: Topic :: Software Development :: Libraries :: Python Modules
Classifier: Environment :: Web Environment
Classifier: Topic :: Internet
Classifier: License :: OSI Approved :: MIT License
Classifier: Operating System :: OS Independent
Classifier: Programming Language :: Python
Classifier: Programming Language :: Python :: 2.7
Classifier: Programming Language :: Python :: 3.5
Classifier: Programming Language :: Python :: 3.6
Classifier: Programming Language :: Python :: 3.7
Classifier: Programming Language :: Python :: 3.8
Classifier: Framework :: Django
Classifier: Framework :: Django :: 1.11
Classifier: Framework :: Django :: 2.0
Classifier: Framework :: Django :: 2.1
Classifier: Framework :: Django :: 2.2
Requires-Dist: Django (>=1.11)
Requires-Dist: django-bootstrap4
Requires-Dist: PyPDF2
Requires-Dist: reportlab
Requires-Dist: six
